fshare/__init__.py
fshare/__main__.py
fshare/cli.py
fshare/filemanager.py
fshare/index.html
fshare/index.js
fshare/main.py
fshare-1.1.3.dist-info/METADATA
fshare-1.1.3.dist-info/WHEEL
fshare-1.1.3.dist-info/top_level.txt
fshare-1.1.3.dist-info/RECORD
