Metadata-Version: 2.1
Name: fshare
Version: 1.1.3
Summary: A python package that serves as an easy file sharing application over local network
Author-email: Stevo Mitric <stevomitric2000@gmail.com>
Maintainer-email: Stevo Mitric <stevomitric2000@gmail.com>
Project-URL: Homepage, https://github.com/stevomitric/fshare
Project-URL: Bug Tracker, https://github.com/stevomitric/fshare/issues
Keywords: file,share
Classifier: Programming Language :: Python :: 3
Classifier: License :: OSI Approved :: MIT License
Classifier: Operating System :: OS Independent
Classifier: Development Status :: 5 - Production/Stable
Classifier: Framework :: Flask
Requires-Python: >=3.0
